bootstrap_admin/__init__.py
bootstrap_admin/static/admin/css/base.css
bootstrap_admin/static/admin/css/changelists.css
bootstrap_admin/static/admin/css/dashboard.css
bootstrap_admin/static/admin/css/datetime_widget.css
bootstrap_admin/static/admin/css/forms.css
bootstrap_admin/static/admin/css/login.css
bootstrap_admin/static/bootstrap_admin/img/logo-140x60.png
bootstrap_admin/static/bootstrap_admin/js/base.js
bootstrap_admin/static/bootstrap_admin/js/dashboard.js
bootstrap_admin/templates/admin/404.html
bootstrap_admin/templates/admin/500.html
bootstrap_admin/templates/admin/actions.html
bootstrap_admin/templates/admin/app_index.html
bootstrap_admin/templates/admin/base.html
bootstrap_admin/templates/admin/base_site.html
bootstrap_admin/templates/admin/change_form.html
bootstrap_admin/templates/admin/change_list.html
bootstrap_admin/templates/admin/change_list_results.html
bootstrap_admin/templates/admin/date_hierarchy.html
bootstrap_admin/templates/admin/delete_confirmation.html
bootstrap_admin/templates/admin/delete_selected_confirmation.html
bootstrap_admin/templates/admin/filter.html
bootstrap_admin/templates/admin/index.html
bootstrap_admin/templates/admin/invalid_setup.html
bootstrap_admin/templates/admin/login.html
bootstrap_admin/templates/admin/object_history.html
bootstrap_admin/templates/admin/pagination.html
bootstrap_admin/templates/admin/popup_response.html
bootstrap_admin/templates/admin/prepopulated_fields_js.html
bootstrap_admin/templates/admin/related_widget_wrapper.html
bootstrap_admin/templates/admin/search_form.html
bootstrap_admin/templates/admin/submit_line.html
bootstrap_admin/templates/admin/auth/user/add_form.html
bootstrap_admin/templates/admin/auth/user/change_password.html
bootstrap_admin/templates/admin/edit_inline/stacked.html
bootstrap_admin/templates/admin/edit_inline/tabular.html
bootstrap_admin/templates/admin/includes/field.html
bootstrap_admin/templates/admin/includes/fieldset.html
bootstrap_admin-0.4.4.dist-info/AUTHORS.rst
bootstrap_admin-0.4.4.dist-info/LICENSE
bootstrap_admin-0.4.4.dist-info/METADATA
bootstrap_admin-0.4.4.dist-info/WHEEL
bootstrap_admin-0.4.4.dist-info/top_level.txt
bootstrap_admin-0.4.4.dist-info/RECORD
