Metadata-Version: 1.1
Name: bootstrap_admin
Version: 0.4.4
Summary: Responsive Theme for Django Admin With Sidebar Menu (Django 1.11)
Home-page: https://github.com/douglasmiranda/django-admin-bootstrap
Author: Douglas Miranda
Author-email: douglascoding@gmail.com
License: BSD
Keywords: django,admin,skin,theme,bootstrap,responsive
Platform: UNKNOWN
Classifier: Development Status :: 5 - Production/Stable
Classifier: Environment :: Web Environment
Classifier: Framework :: Django
Classifier: Intended Audience :: Developers
Classifier: License :: OSI Approved :: MIT License
Classifier: Operating System :: OS Independent
Classifier: Programming Language :: Python
Classifier: Programming Language :: Python :: 2
Classifier: Programming Language :: Python :: 2.7
Classifier: Programming Language :: Python :: 3
Classifier: Programming Language :: Python :: 3.4
Classifier: Programming Language :: Python :: 3.5
Classifier: Programming Language :: Python :: 3.6
